infosec_fools/__init__.py
infosec_fools/main.py
infosec_fools-1.0.1.dist-info/entry_points.txt
infosec_fools-1.0.1.dist-info/LICENSE
infosec_fools-1.0.1.dist-info/WHEEL
infosec_fools-1.0.1.dist-info/METADATA
infosec_fools-1.0.1.dist-info/RECORD
